{
  "_class": "symbolInstance",
  "booleanOperation": 0,
  "do_objectID": "9414C2E7-E0EA-4698-AE52-F43C1F325FC7",
  "exportOptions": {
    "_class": "exportOptions",
    "do_objectID": "186DE912-CEAB-41DF-959F-4F48C28F4597",
    "exportFormats": [
    ],
    "includedLayerIds": [
    ],
    "layerOptions": 0,
    "shouldTrim": false
  },
  "frame": {
    "_class": "rect",
    "constrainProportions": false,
    "do_objectID": "3213DFDB-5D05-4B99-B0BC-7AD44E2457B8",
    "height": 32,
    "width": 148,
    "x": 48,
    "y": 908
  },
  "horizontalSpacing": 0,
  "isFixedToViewport": false,
  "isFlippedHorizontal": false,
  "isFlippedVertical": false,
  "isLocked": false,
  "isVisible": true,
  "layerListExpandedType": 0,
  "name": "button/pink/primary/with icon/standard",
  "nameIsFixed": false,
  "overrideValues": [
  ],
  "resizingConstraint": 63,
  "resizingType": 0,
  "rotation": 0,
  "scale": 1,
  "shouldBreakMaskChain": false,
  "style": {
    "_class": "style",
    "do_objectID": "4D9299E2-4088-4AB1-87EC-880D9C7DE7EC",
    "endMarkerType": 0,
    "miterLimit": 10,
    "startMarkerType": 0,
    "windingRule": 1
  },
  "symbolID": "4BC22501-2C91-4B2B-B54E-97DF382304D3",
  "userInfo": {
    "com.animaapp.stc-sketch-plugin": {
      "kModelPropertiesKey": {
      }
    }
  },
  "verticalSpacing": 0
}