{
  "_class": "symbolInstance",
  "do_objectID": "6B395381-8A7B-40B9-BD5B-76369C36C2AF",
  "exportOptions": {
    "_class": "exportOptions",
    "do_objectID": "D86ADE9A-E6AC-4CAD-8F31-6BE02796F563",
    "exportFormats": [
    ],
    "includedLayerIds": [
    ],
    "layerOptions": 0,
    "shouldTrim": false
  },
  "frame": {
    "_class": "rect",
    "constrainProportions": false,
    "do_objectID": "90B94EF1-1072-41E5-8156-460589BCB4E4",
    "height": 24,
    "width": 24,
    "x": 224,
    "y": 8
  },
  "horizontalSpacing": 0,
  "isFlippedHorizontal": false,
  "isFlippedVertical": false,
  "isLocked": true,
  "isVisible": true,
  "layerListExpandedType": 0,
  "name": "atoms/icons/inline/icon",
  "nameIsFixed": true,
  "overrideValues": [
    {
      "_class": "overrideValue",
      "overrideName": "46E46722-34DB-4C89-87EA-A3383E70D3F1_stringValue",
      "value": "keyboard_arrow_up"
    }
  ],
  "resizingConstraint": 44,
  "resizingType": 0,
  "rotation": 0,
  "scale": 1,
  "shouldBreakMaskChain": false,
  "style": {
    "_class": "style",
    "do_objectID": "9A9DE3CA-237C-4EA5-B3DD-87D177B0674D",
    "endDecorationType": 0,
    "miterLimit": 10,
    "startDecorationType": 0
  },
  "symbolID": "C6BFB6A0-5EAE-4159-A853-EE145C8EED9C",
  "userInfo": {
    "com.animaapp.stc-sketch-plugin": {
      "kModelPropertiesKey": {
      }
    }
  },
  "verticalSpacing": 0
}