{
  "_class": "text",
  "attributedString": {
    "_class": "attributedString",
    "attributes": [
      {
        "_class": "stringAttribute",
        "attributes": {
          "MSAttributedStringColorAttribute": {
            "_class": "color",
            "alpha": 1,
            "blue": 0.3882352941176471,
            "green": 0.384313725490196,
            "red": 0.3803921568627451
          },
          "MSAttributedStringFontAttribute": {
            "_class": "fontDescriptor",
            "attributes": {
              "name": "Roboto-Light",
              "size": 20
            }
          },
          "kerning": 0.300000011920929,
          "paragraphStyle": {
            "_class": "paragraphStyle",
            "alignment": 0,
            "allowsDefaultTighteningForTruncation": 0,
            "maximumLineHeight": 24,
            "minimumLineHeight": 24
          },
          "textStyleVerticalAlignmentKey": 0
        },
        "length": 28,
        "location": 0
      }
    ],
    "string": "Linux Or Windows Which Is It"
  },
  "automaticallyDrawOnUnderlyingPath": false,
  "booleanOperation": 0,
  "do_objectID": "CAFBB91B-A6F3-4AD9-AF31-1245E0112902",
  "dontSynchroniseWithSymbol": false,
  "exportOptions": {
    "_class": "exportOptions",
    "do_objectID": "92AD2F27-EA11-4784-97DD-3F95177AFA8B",
    "exportFormats": [
    ],
    "includedLayerIds": [
    ],
    "layerOptions": 0,
    "shouldTrim": false
  },
  "frame": {
    "_class": "rect",
    "constrainProportions": false,
    "do_objectID": "0C081290-2C64-41F4-851D-19884C29A6DD",
    "height": 24,
    "width": 263,
    "x": 344,
    "y": 108
  },
  "glyphBounds": "{{1, 4}, {261, 16}}",
  "isFixedToViewport": false,
  "isFlippedHorizontal": false,
  "isFlippedVertical": false,
  "isLocked": false,
  "isVisible": true,
  "layerListExpandedType": 0,
  "lineSpacingBehaviour": 2,
  "name": "Linux Or Windows Whi",
  "nameIsFixed": false,
  "resizingConstraint": 47,
  "resizingType": 0,
  "rotation": 0,
  "shouldBreakMaskChain": false,
  "style": {
    "_class": "style",
    "do_objectID": "3FA1876C-9BCD-426B-8D9C-BD645CE76A26",
    "endMarkerType": 0,
    "miterLimit": 10,
    "sharedObjectID": "07CD01AA-2B37-4828-BBB3-4235CBE40674",
    "startMarkerType": 0,
    "textStyle": {
      "_class": "textStyle",
      "encodedAttributes": {
        "MSAttributedStringColorAttribute": {
          "_class": "color",
          "alpha": 1,
          "blue": 0.3882352941176471,
          "green": 0.384313725490196,
          "red": 0.3803921568627451
        },
        "MSAttributedStringFontAttribute": {
          "_class": "fontDescriptor",
          "attributes": {
            "name": "Roboto-Light",
            "size": 20
          }
        },
        "kerning": 0.300000011920929,
        "paragraphStyle": {
          "_class": "paragraphStyle",
          "alignment": 0,
          "allowsDefaultTighteningForTruncation": 0,
          "maximumLineHeight": 24,
          "minimumLineHeight": 24
        },
        "textStyleVerticalAlignmentKey": 0
      },
      "verticalAlignment": 0
    },
    "windingRule": 1
  },
  "textBehaviour": 0,
  "userInfo": {
    "com.animaapp.stc-sketch-plugin": {
      "kModelPropertiesKey": {
        "isAutoWidth": 1
      }
    },
    "com.invisionlabs.duplicate": {
      "type-duplicate": {
        "action": "article",
        "options": {
          "section": "technology",
          "type": "title"
        },
        "title": "Technology"
      }
    }
  }
}